bm25_retriever/__init__.py
bm25_retriever/retriever.py
persistent_bm25_v2-1.0.1.dist-info/METADATA
persistent_bm25_v2-1.0.1.dist-info/WHEEL
persistent_bm25_v2-1.0.1.dist-info/top_level.txt
persistent_bm25_v2-1.0.1.dist-info/RECORD
