Metadata-Version: 2.1
Name: persistent_bm25_v2
Version: 1.0.1
Summary: A persistent implementation of BM25 retrieval.
Home-page: https://github.com/mohammed-orabi2/persistent-bm25
Author: Mohammed Orabi
Author-email: mahmedorabi297@gmail.com
Classifier: Programming Language :: Python :: 3
Classifier: License :: OSI Approved :: MIT License
Classifier: Operating System :: OS Independent
Requires-Python: >=3.7
Requires-Dist: langchain
Requires-Dist: rank-bm25
